LICENSE
MANIFEST.in
README.md
package_info.json
requirements.txt
setup.py
th2_data_services/data_source/lwdp/__init__.py
th2_data_services/data_source/lwdp/init_resolvers_by_import.py
th2_data_services/data_source/lwdp/message_response_format.py
th2_data_services/data_source/lwdp/page.py
th2_data_services/data_source/lwdp/resolver.py
th2_data_services/data_source/lwdp/streams.py
th2_data_services/data_source/lwdp/struct.py
th2_data_services/data_source/lwdp/stub_builder.py
th2_data_services/data_source/lwdp/adapters/__init__.py
th2_data_services/data_source/lwdp/adapters/adapter_sse.py
th2_data_services/data_source/lwdp/commands/__init__.py
th2_data_services/data_source/lwdp/commands/http.py
th2_data_services/data_source/lwdp/data_source/__init__.py
th2_data_services/data_source/lwdp/data_source/http.py
th2_data_services/data_source/lwdp/event_tree/__init__.py
th2_data_services/data_source/lwdp/event_tree/http_etc_driver.py
th2_data_services/data_source/lwdp/filters/__init__.py
th2_data_services/data_source/lwdp/filters/event_filters.py
th2_data_services/data_source/lwdp/filters/filter.py
th2_data_services/data_source/lwdp/interfaces/__init__.py
th2_data_services/data_source/lwdp/interfaces/command.py
th2_data_services/data_source/lwdp/interfaces/data_source.py
th2_data_services/data_source/lwdp/interfaces/filter.py
th2_data_services/data_source/lwdp/interfaces/source_api.py
th2_data_services/data_source/lwdp/source_api/__init__.py
th2_data_services/data_source/lwdp/source_api/http.py
th2_data_services/data_source/lwdp/utils/__init__.py
th2_data_services/data_source/lwdp/utils/_misc.py
th2_data_services/data_source/lwdp/utils/_response_formats.py
th2_data_services/data_source/lwdp/utils/_retry_utils.py
th2_data_services/data_source/lwdp/utils/iter_status_manager.py
th2_data_services_lwdp.egg-info/PKG-INFO
th2_data_services_lwdp.egg-info/SOURCES.txt
th2_data_services_lwdp.egg-info/dependency_links.txt
th2_data_services_lwdp.egg-info/requires.txt
th2_data_services_lwdp.egg-info/top_level.txt