Metadata-Version: 2.1
Name: th2-data-services-lwdp
Version: 3.1.2.2.dev18683034500
Summary: th2_data_services_lwdp
Home-page: https://github.com/th2-net/th2-ds-source-lwdp
Author: TH2-devs
Author-email: th2-devs@exactprosystems.com
License: Apache License 2.0
Requires-Python: >=3.8
License-File: LICENSE
